{"cameraMode":{"drawMode":0,"name":"Shaded","section":"Shading Mode"},"sceneLighting":true,"audioPlay":false,"sceneViewState":{"showFog":true,"showMaterialUpdate":false,"showSkybox":true,"showFlares":true,"showImageEffects":true,"showParticleSystems":true},"in2DMode":false,"pivot":{"x":0.33327746391296389,"y":0.8702117800712586,"z":-0.6576388478279114},"rotation":{"x":-0.045253343880176547,"y":0.9098203778266907,"z":-0.10307396203279495,"w":-0.399444043636322},"size":5.854628086090088,"orthographic":false}